sparsesurv/__init__.py
sparsesurv/_base.py
sparsesurv/aft.py
sparsesurv/baseline_hazard_estimation.py
sparsesurv/compat.py
sparsesurv/constants.py
sparsesurv/cv.py
sparsesurv/eh.py
sparsesurv/gradients.py
sparsesurv/loss.py
sparsesurv/utils.py
sparsesurv-0.1.dist-info/AUTHORS
sparsesurv-0.1.dist-info/LICENSE
sparsesurv-0.1.dist-info/METADATA
sparsesurv-0.1.dist-info/WHEEL
sparsesurv-0.1.dist-info/top_level.txt
sparsesurv-0.1.dist-info/RECORD
