Metadata-Version: 2.1
Name: sparsesurv
Version: 0.1
Summary: Installable sparsesurv package via pip or source. Modify as needed.
Home-page: https://github.com/BoevaLab/sparsesurv
Author-email: dwissel@inf.ethz.ch, jnikita@inf.ethz.ch
License: BSD-3-Clause
Keywords: Survival,Knowledge Distillation,Sparse Survival,High Dimensional Data
Classifier: Topic :: Software Development :: Libraries :: Python Modules
Classifier: License :: OSI Approved :: BSD License
Classifier: Development Status :: 5 - Production/Stable
Classifier: Intended Audience :: Science/Research
Classifier: Operating System :: OS Independent
Classifier: Programming Language :: Python :: 3.8
Classifier: Programming Language :: Python :: 3.9
Classifier: Programming Language :: Python :: 3.10
License-File: LICENSE
License-File: AUTHORS
Requires-Dist: numpy >=1.23.4
Requires-Dist: pandas >=1.5.1
Requires-Dist: celer >=0.7.2
Requires-Dist: numba >=0.56.4
Requires-Dist: scikit-learn >=1.2.1
Provides-Extra: dev
Requires-Dist: pytest ; extra == 'dev'
Requires-Dist: pytest-cov ; extra == 'dev'
Requires-Dist: black ==21.5b0 ; extra == 'dev'
Requires-Dist: flake8 ; extra == 'dev'
Requires-Dist: mypy ; extra == 'dev'
Requires-Dist: sphinx ; extra == 'dev'
Requires-Dist: sphinx-autodoc-typehints ; extra == 'dev'
Requires-Dist: better-apidoc ; extra == 'dev'
Requires-Dist: six ; extra == 'dev'
Requires-Dist: sphinx-rtd-theme ; extra == 'dev'
Requires-Dist: myst-parser ; extra == 'dev'
Provides-Extra: test
Requires-Dist: pytest ; extra == 'test'
Requires-Dist: pytest-cov ; extra == 'test'
Provides-Extra: vcs
